almanac/__init__.py
almanac/apogee.py
almanac/catalog.py
almanac/cli.py
almanac/config.py
almanac/database.py
almanac/display.py
almanac/io.py
almanac/logger.py
almanac/qa.py
almanac/utils.py
almanac/data_models/__init__.py
almanac/data_models/exposure.py
almanac/data_models/fps.py
almanac/data_models/metadata.py
almanac/data_models/plate.py
almanac/data_models/types.py
almanac/data_models/utils.py
almanac/etc/__init__.py
almanac/etc/bad_exposures.csv
almanac/stash/data_models.py
almanac/stash/plugmap_models.py
sdss_almanac-0.3.6.dist-info/licenses/LICENSE.md
sdss_almanac-0.3.6.dist-info/METADATA
sdss_almanac-0.3.6.dist-info/WHEEL
sdss_almanac-0.3.6.dist-info/entry_points.txt
sdss_almanac-0.3.6.dist-info/top_level.txt
sdss_almanac-0.3.6.dist-info/RECORD
