Metadata-Version: 2.4
Name: sdss-almanac
Version: 0.3.6
Summary: Everything we've got
Author-email: Andy Casey <andrew.casey@monash.edu>
License: BSD 3-Clause License
Project-URL: Homepage, https://github.com/sdss/almanac
Project-URL: Documentation, https://sdss-almanac.readthedocs.org
Project-URL: Repository, https://github.com/sdss/almanac
Keywords: astronomy,software
Classifier: Intended Audience :: Science/Research
Classifier: Natural Language :: English
Classifier: Operating System :: OS Independent
Classifier: Programming Language :: Python
Classifier: Programming Language :: Python :: 3.6
Classifier: Programming Language :: Python :: 3.7
Classifier: Programming Language :: Python :: 3.8
Classifier: Topic :: Documentation :: Sphinx
Classifier: Topic :: Software Development :: Libraries :: Python Modules
Requires-Python: >=3.11
License-File: LICENSE.md
Requires-Dist: numpy
Requires-Dist: astropy
Requires-Dist: h5py
Requires-Dist: tqdm
Requires-Dist: click
Requires-Dist: pydl
Requires-Dist: sdssdb
Requires-Dist: colorlog
Requires-Dist: rich
Requires-Dist: pydantic
Provides-Extra: dev
Requires-Dist: ipython>=7.9.0; extra == "dev"
Requires-Dist: matplotlib>=3.1.1; extra == "dev"
Requires-Dist: flake8>=3.7.9; extra == "dev"
Requires-Dist: doc8>=0.8.0; extra == "dev"
Requires-Dist: pytest>=5.2.2; extra == "dev"
Requires-Dist: pytest-asyncio>=0.10.0; extra == "dev"
Requires-Dist: pytest-cov>=2.8.1; extra == "dev"
Requires-Dist: pytest-mock>=1.13.0; extra == "dev"
Requires-Dist: pytest-sugar>=0.9.2; extra == "dev"
Requires-Dist: isort>=4.3.21; extra == "dev"
Requires-Dist: codecov>=2.0.15; extra == "dev"
Requires-Dist: coverage[toml]>=5.0; extra == "dev"
Requires-Dist: ipdb>=0.12.3; extra == "dev"
Requires-Dist: invoke>=1.3.0; extra == "dev"
Requires-Dist: twine>=3.1.1; extra == "dev"
Requires-Dist: wheel>=0.33.6; extra == "dev"
Requires-Dist: sphinx>=3.0.0; extra == "dev"
Provides-Extra: docs
Requires-Dist: Sphinx<8.0.0,>=5.0.0; extra == "docs"
Requires-Dist: furo>=2023.3.27; extra == "docs"
Requires-Dist: sphinx-autodoc-typehints>=1.12.0; extra == "docs"
Requires-Dist: myst-parser>=0.18.0; extra == "docs"
Requires-Dist: sphinxcontrib-bibtex>=2.4.0; extra == "docs"
Requires-Dist: sphinx-copybutton>=0.5.0; extra == "docs"
Requires-Dist: linkify-it-py; extra == "docs"
Dynamic: license-file
